ARSC/__init__.py
ARSC/core.py
ARSC/main.py
ARSC/utils.py
arsc-0.5.0.dist-info/licenses/LICENSE
arsc-0.5.0.dist-info/METADATA
arsc-0.5.0.dist-info/WHEEL
arsc-0.5.0.dist-info/entry_points.txt
arsc-0.5.0.dist-info/top_level.txt
arsc-0.5.0.dist-info/RECORD
