Metadata-Version: 2.4
Name: arsc
Version: 0.5.0
Summary: Compute ARSC (N/C/S) from protein fasta files
Home-page: https://github.com/stsnsn/quickARSC
Author: Satoshi Nishino
Author-email: satoshi-nishino@g.ecc.u-tokyo.ac.jp
License: GPL-2.0
License-File: LICENSE
Requires-Dist: biopython>=1.79
Dynamic: author
Dynamic: author-email
Dynamic: description
Dynamic: description-content-type
Dynamic: home-page
Dynamic: license
Dynamic: license-file
Dynamic: requires-dist
Dynamic: summary
